LICENSE
README.md
connord/__init__.py
connord/areas.py
connord/categories.py
connord/config/01-filter.fallback
connord/config/01-filter.rules
connord/config/01-filter6.fallback
connord/config/01-filter6.rules
connord/config.py
connord/connect.py
connord/connord.py
connord/countries.py
connord/db/connord.sqlite3
connord/exceptions.py
connord/features.py
connord/formatter.py
connord/iptables.py
connord/listings.py
connord/locations.py
connord/openvpn.py
connord/parser/__init__.py
connord/parser/lexer.py
connord/parser/parser.py
connord/printer.py
connord/resources.py
connord/scripts/dump_openvpn_env.bash
connord/scripts/openvpn_ipchange.bash
connord/scripts/openvpn_up_down.bash
connord/scripts/openvpn_up_down_reolvconf.bash
connord/scripts/openvpn_up_down_systemd.bash
connord/scripts/update-systemd-resolved
connord/scripts/update-systemd-resolved.conf
connord/servers.py
connord/sqlite.py
connord/update.py
connord/user.py
connord/version.py
connord/wrappers/__init__.py
connord/wrappers/argparser.py
connord/wrappers/commands.py
connord/wrappers/nettools.py
connord-0.7.1.dist-info/entry_points.txt
connord-0.7.1.dist-info/LICENSE
connord-0.7.1.dist-info/WHEEL
connord-0.7.1.dist-info/METADATA
connord-0.7.1.dist-info/RECORD
