Metadata-Version: 2.1
Name: connord
Version: 0.7.1
Summary: Connect to NordVPN servers
Home-page: https://github.com/MaelStor/connord
License: GPL-3.0-or-later
Keywords: console,dynamic,fast,firewall,iptables,linux,network,nordvpn,openvpn,privacy,security,shell,system,terminal,tool,utility,vpn
Author: Mael Stor
Author-email: maelstor@posteo.de
Requires-Python: >=3.6,<4.0
Classifier: Development Status :: 5 - Production/Stable
Classifier: Environment :: Console
Classifier: Intended Audience :: End Users/Desktop
Classifier: Intended Audience :: System Administrators
Classifier: Intended Audience :: Telecommunications Industry
Classifier: License :: OSI Approved :: GNU General Public License v3 or later (GPLv3+)
Classifier: Natural Language :: English
Classifier: Operating System :: POSIX :: Linux
Classifier: Programming Language :: Python :: 3
Classifier: Programming Language :: Python :: 3.10
Classifier: Programming Language :: Python :: 3.6
Classifier: Programming Language :: Python :: 3.7
Classifier: Programming Language :: Python :: 3.8
Classifier: Programming Language :: Python :: 3.9
Classifier: Topic :: Security
Classifier: Topic :: System :: Networking
Classifier: Topic :: System :: Networking :: Firewalls
Classifier: Topic :: System :: Systems Administration
Classifier: Topic :: Utilities
Requires-Dist: cachetools (>=4.2.4,<5.0.0)
Requires-Dist: jinja2 (>=3,<4)
Requires-Dist: netaddr (>=0.8,<0.9)
Requires-Dist: netifaces (>=0.11.0,<0.12.0)
Requires-Dist: progress (>=1.6,<2.0)
Requires-Dist: python-iptables (>=1.0.0,<2.0.0)
Requires-Dist: pyyaml (>=6.0,<7.0)
Requires-Dist: requests (>=2.26.0,<3.0.0)
Requires-Dist: setuptools (>=57.4.2,<58.0.0)
Project-URL: Documentation, https://github.com/MaelStor/connord
Project-URL: Issues, https://github.com/MaelStor/connord/issues
